{ 
    "_id" : ObjectId("5f1973db4c520000c0006fb8"), 
    "cid" : "5f00955b4a3200009f0060e3", 
    "msg" : "bbfg", 
    "icon" : "fa fa-check", 
    "stime" : NumberInt(1595503579), 
    "sdate" : "2020-07-23", 
    "o" : ObjectId("5f01bb41f21353230445387b"), 
    "oname" : "Hafizul Islam"
}
{ 
    "_id" : ObjectId("5f1973e74c520000c0006fb9"), 
    "cid" : "5f00955b4a3200009f0060e3", 
    "msg" : "ok", 
    "icon" : "fa fa-check", 
    "stime" : NumberInt(1595503591), 
    "sdate" : "2020-07-23", 
    "o" : ObjectId("5f01bb41f21353230445387b"), 
    "oname" : "Hafizul Islam"
}
